msgspec/msgpack.py
msgspec/msgpack.pyi
msgspec/__init__.pyi
msgspec/_version.py
msgspec/__init__.py
msgspec/yaml.py
msgspec/structs.py
msgspec/inspect.py
msgspec/json.pyi
msgspec/_json_schema.py
msgspec/py.typed
msgspec/structs.pyi
msgspec/_core.cpython-311-darwin.so
msgspec/json.py
msgspec/_utils.py
msgspec/toml.py
msgspec-0.18.6.dist-info/RECORD
msgspec-0.18.6.dist-info/LICENSE
msgspec-0.18.6.dist-info/WHEEL
msgspec-0.18.6.dist-info/top_level.txt
msgspec-0.18.6.dist-info/METADATA
