Metadata-Version: 2.1
Name: msgspec
Version: 0.18.6
Summary: A fast serialization and validation library, with builtin support for JSON, MessagePack, YAML, and TOML.
Home-page: https://jcristharif.com/msgspec/
Maintainer: Jim Crist-Harif
Maintainer-email: jcristharif@gmail.com
License: BSD
Project-URL: Documentation, https://jcristharif.com/msgspec/
Project-URL: Source, https://github.com/jcrist/msgspec/
Project-URL: Issue Tracker, https://github.com/jcrist/msgspec/issues
Keywords: JSON msgpack MessagePack TOML YAML serialization validation schema
Platform: UNKNOWN
Classifier: License :: OSI Approved :: BSD License
Classifier: Development Status :: 4 - Beta
Classifier: Programming Language :: Python :: 3.8
Classifier: Programming Language :: Python :: 3.9
Classifier: Programming Language :: Python :: 3.10
Classifier: Programming Language :: Python :: 3.11
Classifier: Programming Language :: Python :: 3.12
Requires-Python: >=3.8
Provides-Extra: yaml
Provides-Extra: toml
Provides-Extra: doc
Provides-Extra: test
Provides-Extra: dev
